cli/__init__.py
cli/ai/__init__.py
cli/ai/claude_analyzer.py
cli/commands.py
cli/core/__init__.py
cli/core/detector.py
cli/core/errors.py
cli/core/logger.py
cli/debug_script.py
cli/formatter/__init__.py
cli/formatter/formatter.py
cli/formatter/interface.py
cli/main.py
cli/models/__init__.py
cli/models/analysis.py
cli/models/profiling.py
cli/profilers/__init__.py
cli/profilers/base.py
cli/profilers/python/__init__.py
cli/profilers/python/scalene_profiler.py
cli/runner/__init__.py
cli/runner/base.py
cli/runner/models.py
cli/runner/python_runner.py
aiprofile-1.0.2.dist-info/METADATA
aiprofile-1.0.2.dist-info/WHEEL
aiprofile-1.0.2.dist-info/entry_points.txt
aiprofile-1.0.2.dist-info/licenses/LICENSE
aiprofile-1.0.2.dist-info/RECORD
