Metadata-Version: 2.4
Name: aiprofile
Version: 1.0.2
Summary: AI-powered Python profiling tool with Claude AI insights and intelligent optimization recommendations
License: MIT
License-File: LICENSE
Keywords: profiling,performance,ai,claude,python,optimization,bottleneck-detection
Author: AI Profile Team
Requires-Python: >=3.9, !=2.7.*, !=3.0.*, !=3.1.*, !=3.2.*, !=3.3.*, !=3.4.*, !=3.5.*, !=3.6.*, !=3.7.*, !=3.8.*
Classifier: Development Status :: 5 - Production/Stable
Classifier: Intended Audience :: Developers
Classifier: Intended Audience :: Science/Research
Classifier: License :: OSI Approved :: MIT License
Classifier: Programming Language :: Python :: 3
Classifier: Programming Language :: Python :: 3.9
Classifier: Programming Language :: Python :: 3.10
Classifier: Programming Language :: Python :: 3.12
Classifier: Programming Language :: Python :: 3.13
Classifier: Programming Language :: Python :: 3.14
Classifier: Programming Language :: Python :: 3.11
Classifier: Topic :: Software Development :: Libraries :: Python Modules
Classifier: Topic :: System :: Monitoring
Requires-Dist: anthropic (>=0.71.0,<0.72.0)
Requires-Dist: click (>=8.0.0,<8.2.0)
Requires-Dist: psutil (>=5.9.0,<6.0.0)
Requires-Dist: pydantic (>=2.0.0,<3.0.0)
Requires-Dist: requests (>=2.31.0,<3.0.0)
Requires-Dist: rich (>=13.0.0,<14.0.0)
Requires-Dist: scalene (>=1.5.0,<2.0.0)
Requires-Dist: tenacity (>=8.2.0,<9.0.0)
Requires-Dist: typer (>=0.9.0,<0.10.0)
